{
  "project": "Vinuspread Jewelry",
  "theme": "Tiffany Luxury Boutique",
  "colors": {
    "brand": {
      "tiffany": { "value": "#70C5BB", "type": "color" }
    },
    "background": {
      "primary": { "value": "#FFFFFF", "type": "color" },
      "ivory": { "value": "#F9F6F0", "type": "color" }
    },
    "text": {
      "deep": { "value": "#171717", "type": "color" },
      "muted": { "value": "#737373", "type": "color" }
    }
  },
  "typography": {
    "fontFamily": {
      "serif": { "value": "Playfair Display, serif", "type": "fontFamily" },
      "sans": { "value": "Inter, sans-serif", "type": "fontFamily" }
    }
  }
}
